{
    "username": "hasaamb@gmail.com",
    "password": "BagChaser415!",
    "headless": false,
    "location": "138 Chillery Avenue, Scarborough",
    "phone": "647-607-4050",
    "notes": {
        "setup": "Copy this file to 'test_input.json' and add your real credentials",
        "security": "Never commit test_input.json to version control",
        "headless": "Set headless to true for background automation",
        "images": "Add your photos to images/ad1/ and images/ad2/ folders"
    }
} 